nonebot_plugin_htmlrender/__init__.py
nonebot_plugin_htmlrender/browser.py
nonebot_plugin_htmlrender/config.py
nonebot_plugin_htmlrender/consts.py
nonebot_plugin_htmlrender/data_source.py
nonebot_plugin_htmlrender/install.py
nonebot_plugin_htmlrender/process.py
nonebot_plugin_htmlrender/signal.py
nonebot_plugin_htmlrender/utils.py
nonebot_plugin_htmlrender/templates/github-markdown-light.css
nonebot_plugin_htmlrender/templates/markdown.html
nonebot_plugin_htmlrender/templates/pygments-default.css
nonebot_plugin_htmlrender/templates/text.css
nonebot_plugin_htmlrender/templates/text.html
nonebot_plugin_htmlrender/templates/katex/katex.min.b64_fonts.css
nonebot_plugin_htmlrender/templates/katex/katex.min.js
nonebot_plugin_htmlrender/templates/katex/mathtex-script-type.min.js
nonebot_plugin_htmlrender/templates/katex/mhchem.min.js
nonebot_plugin_htmlrender-0.6.8.dist-info/METADATA
nonebot_plugin_htmlrender-0.6.8.dist-info/WHEEL
nonebot_plugin_htmlrender-0.6.8.dist-info/licenses/LICENSE
nonebot_plugin_htmlrender-0.6.8.dist-info/RECORD
