Metadata-Version: 2.4
Name: nonebot-plugin-htmlrender
Version: 0.6.8
Summary: 通过浏览器渲染图片
Project-URL: Homepage, https://github.com/kexue-z/nonebot-plugin-htmlrender
Project-URL: Bug Tracker, https://github.com/kexue-z/nonebot-plugin-htmlrender/issues
Author-email: kexue <x@kexue-cloud.cn>
License: MIT License
License-File: LICENSE
Requires-Python: <4.0,>=3.9
Requires-Dist: aiofiles>=0.8.0
Requires-Dist: jinja2>=3.0.3
Requires-Dist: markdown>=3.3.6
Requires-Dist: nonebot-plugin-localstore>=0.7.4
Requires-Dist: nonebot2>=2.4.2
Requires-Dist: playwright>=1.48.0
Requires-Dist: pygments>=2.10.0
Requires-Dist: pymdown-extensions>=9.1
Requires-Dist: python-markdown-math>=0.8
